[
  {
    "day": 72,
    "book": "Judges",
    "chapter": 7,
    "reference": "Judges 7:2",
    "question": "Why did the Lord reduce Gideon's army?",
    "option_a": "So Israel would not boast",
    "option_b": "They lacked weapons",
    "option_c": "They were tired",
    "option_d": "They were outnumbered",
    "correct_answer": "A",
    "difficulty": "easy",
    "tags": ["gideon"]
  },
  {
    "day": 72,
    "book": "Judges",
    "chapter": 7,
    "reference": "Judges 7:7",
    "question": "How many men did Gideon take into battle?",
    "option_a": "300",
    "option_b": "1000",
    "option_c": "500",
    "option_d": "700",
    "correct_answer": "A",
    "difficulty": "medium",
    "tags": ["battle"]
  },
  {
    "day": 72,
    "book": "Judges",
    "chapter": 7,
    "reference": "Judges 7:20",
    "question": "What did Gideon's men shout?",
    "option_a": "A sword for the Lord and for Gideon",
    "option_b": "Victory is ours",
    "option_c": "Fight for Israel",
    "option_d": "The Lord reigns",
    "correct_answer": "A",
    "difficulty": "hard",
    "tags": ["battle"]
  },
  {
    "day": 72,
    "book": "Judges",
    "chapter": 8,
    "reference": "Judges 8:4",
    "question": "What condition were Gideon and his men in while pursuing the enemy?",
    "option_a": "Exhausted",
    "option_b": "Strong",
    "option_c": "Hungry",
    "option_d": "Confident",
    "correct_answer": "A",
    "difficulty": "easy",
    "tags": ["battle"]
  },
  {
    "day": 72,
    "book": "Judges",
    "chapter": 8,
    "reference": "Judges 8:22",
    "question": "What did the Israelites ask Gideon to do?",
    "option_a": "Rule over them",
    "option_b": "Lead them in battle",
    "option_c": "Judge them",
    "option_d": "Teach them",
    "correct_answer": "A",
    "difficulty": "medium",
    "tags": ["leadership"]
  },
  {
    "day": 72,
    "book": "Judges",
    "chapter": 8,
    "reference": "Judges 8:27",
    "question": "What did Gideon make that became a snare?",
    "option_a": "An ephod",
    "option_b": "An altar",
    "option_c": "A sword",
    "option_d": "A crown",
    "correct_answer": "A",
    "difficulty": "hard",
    "tags": ["idolatry"]
  },
  {
    "day": 72,
    "book": "Judges",
    "chapter": 9,
    "reference": "Judges 9:1",
    "question": "Who sought to become king?",
    "option_a": "Abimelek",
    "option_b": "Gideon",
    "option_c": "Jotham",
    "option_d": "Zebah",
    "correct_answer": "A",
    "difficulty": "easy",
    "tags": ["leadership"]
  },
  {
    "day": 72,
    "book": "Judges",
    "chapter": 9,
    "reference": "Judges 9:5",
    "question": "What did Abimelek do to his brothers?",
    "option_a": "Killed them",
    "option_b": "Exiled them",
    "option_c": "Ignored them",
    "option_d": "Captured them",
    "correct_answer": "A",
    "difficulty": "medium",
    "tags": ["violence"]
  },
  {
    "day": 72,
    "book": "Judges",
    "chapter": 9,
    "reference": "Judges 9:8",
    "question": "What did Jotham tell the people?",
    "option_a": "A parable of trees",
    "option_b": "A warning",
    "option_c": "A prophecy",
    "option_d": "A command",
    "correct_answer": "A",
    "difficulty": "hard",
    "tags": ["parable"]
  },
  {
    "day": 72,
    "book": "Judges",
    "chapter": 9,
    "reference": "Judges 9:53",
    "question": "How was Abimelek fatally wounded?",
    "option_a": "A millstone dropped on his head",
    "option_b": "A sword",
    "option_c": "An arrow",
    "option_d": "Fire",
    "correct_answer": "A",
    "difficulty": "hard",
    "tags": ["death"]
  },
  {
    "day": 72,
    "book": "Judges",
    "chapter": 7,
    "reference": "Judges 7:13",
    "question": "What did the Midianite dream about?",
    "option_a": "A loaf of bread",
    "option_b": "A sword",
    "option_c": "A mountain",
    "option_d": "A fire",
    "correct_answer": "A",
    "difficulty": "medium",
    "tags": ["dream"]
  },
  {
    "day": 72,
    "book": "Judges",
    "chapter": 8,
    "reference": "Judges 8:35",
    "question": "What did Israel not show to Gideon's family?",
    "option_a": "Kindness",
    "option_b": "Honor",
    "option_c": "Respect",
    "option_d": "Support",
    "correct_answer": "A",
    "difficulty": "hard",
    "tags": ["failure"]
  }
]