[
  {
    "day": 150,
    "book": "Job",
    "chapter": 28,
    "reference": "Job 28:1",
    "question": "What does Job describe as being mined from the earth?",
    "option_a": "Food",
    "option_b": "Silver",
    "option_c": "Water",
    "option_d": "Wood",
    "correct_answer": "B",
    "difficulty": "easy",
    "tags": ["wisdom"]
  },
  {
    "day": 150,
    "book": "Job",
    "chapter": 28,
    "reference": "Job 28:12",
    "question": "What question is asked about wisdom?",
    "option_a": "Who has it?",
    "option_b": "Where shall wisdom be found?",
    "option_c": "How is it taught?",
    "option_d": "Why is it hidden?",
    "correct_answer": "B",
    "difficulty": "medium",
    "tags": ["wisdom"]
  },
  {
    "day": 150,
    "book": "Job",
    "chapter": 28,
    "reference": "Job 28:18",
    "question": "How is the value of wisdom compared?",
    "option_a": "Less than gold",
    "option_b": "Equal to silver",
    "option_c": "Above jewels",
    "option_d": "Worthless",
    "correct_answer": "C",
    "difficulty": "hard",
    "tags": ["wisdom"]
  },
  {
    "day": 150,
    "book": "Job",
    "chapter": 28,
    "reference": "Job 28:28",
    "question": "What is described as wisdom?",
    "option_a": "Knowledge",
    "option_b": "Fear of the Lord",
    "option_c": "Strength",
    "option_d": "Wealth",
    "correct_answer": "B",
    "difficulty": "hard",
    "tags": ["wisdom"]
  },
  {
    "day": 150,
    "book": "Job",
    "chapter": 29,
    "reference": "Job 29:2",
    "question": "What did Job long for from his past?",
    "option_a": "His wealth",
    "option_b": "The days when God watched over him",
    "option_c": "His youth",
    "option_d": "His family",
    "correct_answer": "B",
    "difficulty": "easy",
    "tags": ["memory"]
  },
  {
    "day": 150,
    "book": "Job",
    "chapter": 29,
    "reference": "Job 29:7",
    "question": "Where did Job take his seat among the people?",
    "option_a": "The temple",
    "option_b": "The city gate",
    "option_c": "The palace",
    "option_d": "The field",
    "correct_answer": "B",
    "difficulty": "medium",
    "tags": ["status"]
  },
  {
    "day": 150,
    "book": "Job",
    "chapter": 29,
    "reference": "Job 29:12",
    "question": "Whom did Job deliver?",
    "option_a": "The rich",
    "option_b": "The poor and fatherless",
    "option_c": "The soldiers",
    "option_d": "The kings",
    "correct_answer": "B",
    "difficulty": "hard",
    "tags": ["justice"]
  },
  {
    "day": 150,
    "book": "Job",
    "chapter": 30,
    "reference": "Job 30:1",
    "question": "Who now mocked Job?",
    "option_a": "Kings",
    "option_b": "Younger men",
    "option_c": "Priests",
    "option_d": "Friends",
    "correct_answer": "B",
    "difficulty": "easy",
    "tags": ["suffering"]
  },
  {
    "day": 150,
    "book": "Job",
    "chapter": 30,
    "reference": "Job 30:9",
    "question": "What had Job become to others?",
    "option_a": "A leader",
    "option_b": "A byword and mockery",
    "option_c": "A teacher",
    "option_d": "A king",
    "correct_answer": "B",
    "difficulty": "medium",
    "tags": ["suffering"]
  },
  {
    "day": 150,
    "book": "Job",
    "chapter": 30,
    "reference": "Job 30:16",
    "question": "How did Job describe his soul?",
    "option_a": "Strong",
    "option_b": "Poured out within him",
    "option_c": "Joyful",
    "option_d": "Peaceful",
    "correct_answer": "B",
    "difficulty": "hard",
    "tags": ["lament"]
  },
  {
    "day": 150,
    "book": "Job",
    "chapter": 30,
    "reference": "Job 30:20",
    "question": "What did Job say God did when he cried for help?",
    "option_a": "Answered him",
    "option_b": "Ignored him",
    "option_c": "Punished him",
    "option_d": "Encouraged him",
    "correct_answer": "B",
    "difficulty": "hard",
    "tags": ["lament"]
  },
  {
    "day": 150,
    "book": "Job",
    "chapter": 29,
    "reference": "Job 29:14",
    "question": "How did Job describe his righteousness and justice?",
    "option_a": "As a shield",
    "option_b": "As clothing and a robe",
    "option_c": "As a weapon",
    "option_d": "As a crown",
    "correct_answer": "B",
    "difficulty": "medium",
    "tags": ["righteousness"]
  }
]