[
  {
    "day": 136,
    "book": "Nehemiah",
    "chapter": 7,
    "reference": "Nehemiah 7:2",
    "question": "Who did Nehemiah put in charge of Jerusalem?",
    "option_a": "Ezra",
    "option_b": "Hanani and Hananiah",
    "option_c": "Sanballat",
    "option_d": "Tobiah",
    "correct_answer": "B",
    "difficulty": "easy",
    "tags": ["leadership"]
  },
  {
    "day": 136,
    "book": "Nehemiah",
    "chapter": 7,
    "reference": "Nehemiah 7:4",
    "question": "How was the city of Jerusalem described after the wall was built?",
    "option_a": "Crowded",
    "option_b": "Large but sparsely populated",
    "option_c": "Destroyed",
    "option_d": "Wealthy",
    "correct_answer": "B",
    "difficulty": "medium",
    "tags": ["jerusalem"]
  },
  {
    "day": 136,
    "book": "Nehemiah",
    "chapter": 7,
    "reference": "Nehemiah 7:5",
    "question": "What did God put into Nehemiah’s heart to do?",
    "option_a": "Build another wall",
    "option_b": "Register the people by genealogy",
    "option_c": "Start a war",
    "option_d": "Leave Jerusalem",
    "correct_answer": "B",
    "difficulty": "hard",
    "tags": ["genealogy"]
  },
  {
    "day": 136,
    "book": "Nehemiah",
    "chapter": 8,
    "reference": "Nehemiah 8:1",
    "question": "Where did the people gather to hear the Law read?",
    "option_a": "The temple",
    "option_b": "The Water Gate",
    "option_c": "The palace",
    "option_d": "The market",
    "correct_answer": "B",
    "difficulty": "easy",
    "tags": ["law"]
  },
  {
    "day": 136,
    "book": "Nehemiah",
    "chapter": 8,
    "reference": "Nehemiah 8:3",
    "question": "From when until when did Ezra read the Law?",
    "option_a": "Morning until midday",
    "option_b": "Noon until evening",
    "option_c": "Evening until night",
    "option_d": "All night",
    "correct_answer": "A",
    "difficulty": "medium",
    "tags": ["law"]
  },
  {
    "day": 136,
    "book": "Nehemiah",
    "chapter": 8,
    "reference": "Nehemiah 8:8",
    "question": "How was the Law explained to the people?",
    "option_a": "It was ignored",
    "option_b": "It was translated and explained clearly",
    "option_c": "It was sung",
    "option_d": "It was rewritten",
    "correct_answer": "B",
    "difficulty": "hard",
    "tags": ["understanding"]
  },
  {
    "day": 136,
    "book": "Nehemiah",
    "chapter": 8,
    "reference": "Nehemiah 8:10",
    "question": "What did Nehemiah say is the strength of the people?",
    "option_a": "Their army",
    "option_b": "Their wealth",
    "option_c": "The joy of the Lord",
    "option_d": "Their city",
    "correct_answer": "C",
    "difficulty": "easy",
    "tags": ["joy"]
  },
  {
    "day": 136,
    "book": "Nehemiah",
    "chapter": 9,
    "reference": "Nehemiah 9:1",
    "question": "What did the Israelites do on the twenty-fourth day?",
    "option_a": "Celebrated",
    "option_b": "Fasted and confessed sins",
    "option_c": "Built walls",
    "option_d": "Traveled",
    "correct_answer": "B",
    "difficulty": "medium",
    "tags": ["repentance"]
  },
  {
    "day": 136,
    "book": "Nehemiah",
    "chapter": 9,
    "reference": "Nehemiah 9:6",
    "question": "What did the people declare about God?",
    "option_a": "He is distant",
    "option_b": "He alone is the Lord and creator",
    "option_c": "He is unknown",
    "option_d": "He is weak",
    "correct_answer": "B",
    "difficulty": "hard",
    "tags": ["creation"]
  },
  {
    "day": 136,
    "book": "Nehemiah",
    "chapter": 9,
    "reference": "Nehemiah 9:17",
    "question": "How is God described despite the people’s disobedience?",
    "option_a": "Angry only",
    "option_b": "Harsh",
    "option_c": "Ready to forgive, gracious and merciful",
    "option_d": "Silent",
    "correct_answer": "C",
    "difficulty": "hard",
    "tags": ["character"]
  },
  {
    "day": 136,
    "book": "Nehemiah",
    "chapter": 7,
    "reference": "Nehemiah 7:65",
    "question": "What were some people not allowed to do because their genealogy was uncertain?",
    "option_a": "Work",
    "option_b": "Fight",
    "option_c": "Eat from the most holy things",
    "option_d": "Travel",
    "correct_answer": "C",
    "difficulty": "medium",
    "tags": ["genealogy"]
  },
  {
    "day": 136,
    "book": "Nehemiah",
    "chapter": 8,
    "reference": "Nehemiah 8:17",
    "question": "What feast did the Israelites celebrate with great joy?",
    "option_a": "Passover",
    "option_b": "Feast of Booths",
    "option_c": "Day of Atonement",
    "option_d": "Feast of Trumpets",
    "correct_answer": "B",
    "difficulty": "easy",
    "tags": ["feasts"]
  }
]