[
  {
    "day": 95,
    "book": "2 Samuel",
    "chapter": 22,
    "reference": "2 Samuel 22",
    "question": "What is the main theme of David’s song in this chapter?",
    "option_a": "War",
    "option_b": "Praise and deliverance",
    "option_c": "Law",
    "option_d": "Judgment",
    "correct_answer": "B",
    "difficulty": "easy",
    "tags": ["song"]
  },
  {
    "day": 95,
    "book": "2 Samuel",
    "chapter": 23,
    "reference": "2 Samuel 23",
    "question": "What are David’s final recorded words called?",
    "option_a": "A prophecy",
    "option_b": "A song",
    "option_c": "A blessing",
    "option_d": "A lament",
    "correct_answer": "A",
    "difficulty": "easy",
    "tags": ["words"]
  },
  {
    "day": 95,
    "book": "2 Samuel",
    "chapter": 24,
    "reference": "2 Samuel 24",
    "question": "What did David order that led to judgment?",
    "option_a": "A battle",
    "option_b": "A census",
    "option_c": "A sacrifice",
    "option_d": "A feast",
    "correct_answer": "B",
    "difficulty": "easy",
    "tags": ["events"]
  },
  {
    "day": 95,
    "book": "2 Samuel",
    "chapter": 22,
    "reference": "2 Samuel 22",
    "question": "What does David call the Lord in his song?",
    "option_a": "Teacher",
    "option_b": "Rock",
    "option_c": "Servant",
    "option_d": "Warrior",
    "correct_answer": "B",
    "difficulty": "medium",
    "tags": ["titles"]
  },
  {
    "day": 95,
    "book": "2 Samuel",
    "chapter": 22,
    "reference": "2 Samuel 22",
    "question": "From what did the Lord deliver David?",
    "option_a": "Famine",
    "option_b": "Enemies and Saul",
    "option_c": "Plague",
    "option_d": "Exile",
    "correct_answer": "B",
    "difficulty": "medium",
    "tags": ["deliverance"]
  },
  {
    "day": 95,
    "book": "2 Samuel",
    "chapter": 23,
    "reference": "2 Samuel 23",
    "question": "What group of men is highlighted for their bravery?",
    "option_a": "Priests",
    "option_b": "Prophets",
    "option_c": "Mighty men",
    "option_d": "Elders",
    "correct_answer": "C",
    "difficulty": "medium",
    "tags": ["people"]
  },
  {
    "day": 95,
    "book": "2 Samuel",
    "chapter": 23,
    "reference": "2 Samuel 23",
    "question": "What did three of David’s men risk their lives to get for him?",
    "option_a": "Gold",
    "option_b": "Water from Bethlehem",
    "option_c": "Food",
    "option_d": "Weapons",
    "correct_answer": "B",
    "difficulty": "medium",
    "tags": ["events"]
  },
  {
    "day": 95,
    "book": "2 Samuel",
    "chapter": 24,
    "reference": "2 Samuel 24",
    "question": "Who warned David that the census was wrong?",
    "option_a": "Nathan",
    "option_b": "Joab",
    "option_c": "Zadok",
    "option_d": "Gad",
    "correct_answer": "B",
    "difficulty": "medium",
    "tags": ["warning"]
  },
  {
    "day": 95,
    "book": "2 Samuel",
    "chapter": 24,
    "reference": "2 Samuel 24",
    "question": "Who gave David options for punishment?",
    "option_a": "Nathan",
    "option_b": "Gad",
    "option_c": "Samuel",
    "option_d": "Joab",
    "correct_answer": "B",
    "difficulty": "medium",
    "tags": ["prophet"]
  },
  {
    "day": 95,
    "book": "2 Samuel",
    "chapter": 22,
    "reference": "2 Samuel 22",
    "question": "What imagery is used to describe God’s power?",
    "option_a": "Wind only",
    "option_b": "Fire, storm, and earth shaking",
    "option_c": "Water only",
    "option_d": "Silence",
    "correct_answer": "B",
    "difficulty": "hard",
    "tags": ["imagery"]
  },
  {
    "day": 95,
    "book": "2 Samuel",
    "chapter": 23,
    "reference": "2 Samuel 23",
    "question": "What did David do with the water brought to him?",
    "option_a": "Drank it",
    "option_b": "Shared it",
    "option_c": "Poured it out to the Lord",
    "option_d": "Stored it",
    "correct_answer": "C",
    "difficulty": "hard",
    "tags": ["worship"]
  },
  {
    "day": 95,
    "book": "2 Samuel",
    "chapter": 23",
    "reference": "2 Samuel 23",
    "question": "What is said about a righteous ruler?",
    "option_a": "He rules with fear",
    "option_b": "He rules in the fear of God",
    "option_c": "He rules alone",
    "option_d": "He rules with power",
    "correct_answer": "B",
    "difficulty": "hard",
    "tags": ["principle"]
  },
  {
    "day": 95,
    "book": "2 Samuel",
    "chapter": 24,
    "reference": "2 Samuel 24",
    "question": "Where did David build an altar to stop the plague?",
    "option_a": "Temple",
    "option_b": "Threshing floor of Araunah",
    "option_c": "Jerusalem gate",
    "option_d": "Hebron",
    "correct_answer": "B",
    "difficulty": "hard",
    "tags": ["locations"]
  },
  {
    "day": 95,
    "book": "2 Samuel",
    "chapter": 24,
    "reference": "2 Samuel 24",
    "question": "What did David insist on doing when buying the altar site?",
    "option_a": "Taking it for free",
    "option_b": "Paying full price",
    "option_c": "Trading land",
    "option_d": "Sharing it",
    "correct_answer": "B",
    "difficulty": "hard",
    "tags": ["principle"]
  }
]