[
  {
    "type": "who_said_it",
    "book": "Matthew",
    "book_order": 40,
    "testament": "new_testament",
    "category": "gospels",
    "speaker": "Angel of the Lord",
    "speaker_type": "angel",
    "reference": "Matthew 1:20",
    "quote_text": "Do not be afraid to take Mary as your wife.",
    "prompt_context": "In a dream, Joseph was told not to fear taking Mary because the child was from the Holy Spirit.",
    "question": "Who told Joseph in a dream not to be afraid to take Mary as his wife?",
    "option_a": "Zechariah",
    "option_b": "Angel of the Lord",
    "option_c": "Mary",
    "option_d": "Joseph",
    "correct_answer": "Angel of the Lord",
    "difficulty": "easy",
    "tags": ["matthew", "angel_of_the_lord", "joseph", "speaker_recognition"],
    "source_key": "matthew-001-angel-joseph-take-mary"
  },
  {
    "type": "who_said_it",
    "book": "Matthew",
    "book_order": 40,
    "testament": "new_testament",
    "category": "gospels",
    "speaker": "Herod",
    "speaker_type": "person",
    "reference": "Matthew 2:8",
    "quote_text": "Bring me word, so that I too may come and worship him.",
    "prompt_context": "After the magi arrived, the ruler of Judea sent them to Bethlehem with secret intentions.",
    "question": "Who told the magi to report back after finding the child in Bethlehem?",
    "option_a": "Chief Priests",
    "option_b": "Joseph",
    "option_c": "Herod",
    "option_d": "Angel of the Lord",
    "correct_answer": "Herod",
    "difficulty": "medium",
    "tags": ["matthew", "herod", "magi", "speaker_recognition"],
    "source_key": "matthew-002-herod-report-back-bethlehem"
  },
  {
    "type": "who_said_it",
    "book": "Matthew",
    "book_order": 40,
    "testament": "new_testament",
    "category": "gospels",
    "speaker": "John the Baptist",
    "speaker_type": "person",
    "reference": "Matthew 3:2",
    "quote_text": "Repent, for the kingdom of heaven has come near.",
    "prompt_context": "In the wilderness of Judea, a preacher called people to prepare for God's reign.",
    "question": "Who called people in the wilderness to repent because the kingdom of heaven was near?",
    "option_a": "John the Baptist",
    "option_b": "Jesus",
    "option_c": "Isaiah",
    "option_d": "Peter",
    "correct_answer": "John the Baptist",
    "difficulty": "easy",
    "tags": ["matthew", "john_the_baptist", "wilderness", "speaker_recognition"],
    "source_key": "matthew-003-john-repent-kingdom-near"
  },
  {
    "type": "who_said_it",
    "book": "Matthew",
    "book_order": 40,
    "testament": "new_testament",
    "category": "gospels",
    "speaker": "Voice from Heaven",
    "speaker_type": "divine",
    "reference": "Matthew 3:17",
    "quote_text": "This is my Son, the Beloved.",
    "prompt_context": "After Jesus was baptized, a voice from heaven publicly identified him.",
    "question": "Who declared from heaven that Jesus was the beloved Son after his baptism?",
    "option_a": "John the Baptist",
    "option_b": "Angel of the Lord",
    "option_c": "Voice from Heaven",
    "option_d": "Jesus",
    "correct_answer": "Voice from Heaven",
    "difficulty": "easy",
    "tags": ["matthew", "voice_from_heaven", "baptism", "speaker_recognition"],
    "source_key": "matthew-004-voice-heaven-beloved-son"
  },
  {
    "type": "who_said_it",
    "book": "Matthew",
    "book_order": 40,
    "testament": "new_testament",
    "category": "gospels",
    "speaker": "Satan",
    "speaker_type": "person",
    "reference": "Matthew 4:3",
    "quote_text": "If you are the Son of God, command these stones to become bread.",
    "prompt_context": "During Jesus' fast in the wilderness, the tempter challenged him to use his power for himself.",
    "question": "Who challenged Jesus in the wilderness to turn stones into bread?",
    "option_a": "John the Baptist",
    "option_b": "Satan",
    "option_c": "Peter",
    "option_d": "Angel of the Lord",
    "correct_answer": "Satan",
    "difficulty": "easy",
    "tags": ["matthew", "satan", "temptation", "speaker_recognition"],
    "source_key": "matthew-005-satan-stones-to-bread"
  },
  {
    "type": "who_said_it",
    "book": "Matthew",
    "book_order": 40,
    "testament": "new_testament",
    "category": "gospels",
    "speaker": "Jesus",
    "speaker_type": "person",
    "reference": "Matthew 4:19",
    "quote_text": "Follow me, and I will make you fish for people.",
    "prompt_context": "By the Sea of Galilee, Simon Peter and Andrew were called away from their nets.",
    "question": "Who told Simon Peter and Andrew that he would make them fish for people?",
    "option_a": "John the Baptist",
    "option_b": "Andrew",
    "option_c": "Jesus",
    "option_d": "Peter",
    "correct_answer": "Jesus",
    "difficulty": "easy",
    "tags": ["matthew", "jesus", "disciples", "speaker_recognition"],
    "source_key": "matthew-006-jesus-fish-for-people"
  },
  {
    "type": "who_said_it",
    "book": "Matthew",
    "book_order": 40,
    "testament": "new_testament",
    "category": "gospels",
    "speaker": "Jesus",
    "speaker_type": "person",
    "reference": "Matthew 5:14",
    "quote_text": "You are the light of the world.",
    "prompt_context": "In the Sermon on the Mount, the speaker described his followers as visible and influential.",
    "question": "Who told his listeners in the Sermon on the Mount, \"You are the light of the world\"?",
    "option_a": "Jesus",
    "option_b": "John the Baptist",
    "option_c": "Peter",
    "option_d": "Moses",
    "correct_answer": "Jesus",
    "difficulty": "easy",
    "tags": ["matthew", "jesus", "sermon_on_the_mount", "speaker_recognition"],
    "source_key": "matthew-007-jesus-light-of-world"
  },
  {
    "type": "who_said_it",
    "book": "Matthew",
    "book_order": 40,
    "testament": "new_testament",
    "category": "gospels",
    "speaker": "Centurion",
    "speaker_type": "person",
    "reference": "Matthew 8:8",
    "quote_text": "I am not worthy to have you come under my roof.",
    "prompt_context": "A Roman officer appealed for healing and expressed confidence that Jesus could heal by command alone.",
    "question": "Who told Jesus he was not worthy to have him come under his roof?",
    "option_a": "Jairus",
    "option_b": "Peter",
    "option_c": "Centurion",
    "option_d": "Matthew",
    "correct_answer": "Centurion",
    "difficulty": "easy",
    "tags": ["matthew", "centurion", "healing", "speaker_recognition"],
    "source_key": "matthew-008-centurion-under-my-roof"
  },
  {
    "type": "who_said_it",
    "book": "Matthew",
    "book_order": 40,
    "testament": "new_testament",
    "category": "gospels",
    "speaker": "Demons",
    "speaker_type": "group",
    "reference": "Matthew 8:29",
    "quote_text": "What have you to do with us, Son of God?",
    "prompt_context": "In the country of the Gadarenes, evil spirits confronted Jesus before he cast them out.",
    "question": "Who cried out to Jesus in the region of the Gadarenes, calling him the Son of God?",
    "option_a": "Crowd",
    "option_b": "Disciples",
    "option_c": "Scribes",
    "option_d": "Demons",
    "correct_answer": "Demons",
    "difficulty": "medium",
    "tags": ["matthew", "demons", "gadarenes", "speaker_recognition"],
    "source_key": "matthew-009-demons-son-of-god"
  },
  {
    "type": "who_said_it",
    "book": "Matthew",
    "book_order": 40,
    "testament": "new_testament",
    "category": "gospels",
    "speaker": "Jesus",
    "speaker_type": "person",
    "reference": "Matthew 9:9",
    "quote_text": "Follow me.",
    "prompt_context": "At the tax booth, the teacher called Matthew away from his work.",
    "question": "Who told Matthew at the tax booth, \"Follow me\"?",
    "option_a": "Peter",
    "option_b": "John the Baptist",
    "option_c": "Jesus",
    "option_d": "Centurion",
    "correct_answer": "Jesus",
    "difficulty": "easy",
    "tags": ["matthew", "jesus", "matthew", "speaker_recognition"],
    "source_key": "matthew-010-jesus-follow-me-matthew"
  },
  {
    "type": "who_said_it",
    "book": "Matthew",
    "book_order": 40,
    "testament": "new_testament",
    "category": "gospels",
    "speaker": "Disciples of John the Baptist",
    "speaker_type": "group",
    "reference": "Matthew 9:14",
    "quote_text": "Why do we and the Pharisees fast often, but your disciples do not fast?",
    "prompt_context": "A question was brought to Jesus comparing his disciples with other religious groups.",
    "question": "Who asked Jesus why his disciples did not fast as often as others?",
    "option_a": "Pharisees",
    "option_b": "Disciples of John the Baptist",
    "option_c": "Chief Priests",
    "option_d": "Crowd",
    "correct_answer": "Disciples of John the Baptist",
    "difficulty": "medium",
    "tags": ["matthew", "disciples_of_john", "fasting", "speaker_recognition"],
    "source_key": "matthew-011-johns-disciples-fasting-question"
  },
  {
    "type": "who_said_it",
    "book": "Matthew",
    "book_order": 40,
    "testament": "new_testament",
    "category": "gospels",
    "speaker": "Jesus",
    "speaker_type": "person",
    "reference": "Matthew 10:16",
    "quote_text": "I am sending you out like sheep into the midst of wolves.",
    "prompt_context": "While commissioning the twelve, the speaker warned them about danger and opposition.",
    "question": "Who warned the twelve that he was sending them out like sheep among wolves?",
    "option_a": "Peter",
    "option_b": "John the Baptist",
    "option_c": "Jesus",
    "option_d": "Moses",
    "correct_answer": "Jesus",
    "difficulty": "medium",
    "tags": ["matthew", "jesus", "twelve", "speaker_recognition"],
    "source_key": "matthew-012-jesus-sheep-among-wolves"
  },
  {
    "type": "who_said_it",
    "book": "Matthew",
    "book_order": 40,
    "testament": "new_testament",
    "category": "gospels",
    "speaker": "John the Baptist",
    "speaker_type": "person",
    "reference": "Matthew 11:3",
    "quote_text": "Are you the one who is to come?",
    "prompt_context": "From prison, a question was sent to Jesus through John's followers.",
    "question": "Who sent word to Jesus asking whether he was the one who was to come?",
    "option_a": "Peter",
    "option_b": "John the Baptist",
    "option_c": "Herod",
    "option_d": "Joseph",
    "correct_answer": "John the Baptist",
    "difficulty": "medium",
    "tags": ["matthew", "john_the_baptist", "prison", "speaker_recognition"],
    "source_key": "matthew-013-john-are-you-the-one"
  },
  {
    "type": "who_said_it",
    "book": "Matthew",
    "book_order": 40,
    "testament": "new_testament",
    "category": "gospels",
    "speaker": "Pharisees",
    "speaker_type": "group",
    "reference": "Matthew 12:2",
    "quote_text": "Your disciples are doing what is not lawful to do on the sabbath.",
    "prompt_context": "After the disciples plucked grain on the sabbath, a religious group challenged Jesus.",
    "question": "Who objected to Jesus because his disciples were plucking grain on the sabbath?",
    "option_a": "Sadducees",
    "option_b": "Disciples",
    "option_c": "Crowd",
    "option_d": "Pharisees",
    "correct_answer": "Pharisees",
    "difficulty": "medium",
    "tags": ["matthew", "pharisees", "sabbath", "speaker_recognition"],
    "source_key": "matthew-014-pharisees-sabbath-grain"
  },
  {
    "type": "who_said_it",
    "book": "Matthew",
    "book_order": 40,
    "testament": "new_testament",
    "category": "gospels",
    "speaker": "Disciples",
    "speaker_type": "group",
    "reference": "Matthew 13:10",
    "quote_text": "Why do you speak to them in parables?",
    "prompt_context": "After Jesus taught the crowds by the sea, a close group asked him about his method.",
    "question": "Who asked Jesus why he spoke to the crowds in parables?",
    "option_a": "Pharisees",
    "option_b": "Scribes",
    "option_c": "Disciples",
    "option_d": "Chief Priests",
    "correct_answer": "Disciples",
    "difficulty": "medium",
    "tags": ["matthew", "disciples", "parables", "speaker_recognition"],
    "source_key": "matthew-015-disciples-why-parables"
  },
  {
    "type": "who_said_it",
    "book": "Matthew",
    "book_order": 40,
    "testament": "new_testament",
    "category": "gospels",
    "speaker": "People of Nazareth",
    "speaker_type": "group",
    "reference": "Matthew 13:55",
    "quote_text": "Is not this the carpenter's son?",
    "prompt_context": "When Jesus taught in his hometown synagogue, local people reacted with skepticism about his background.",
    "question": "Who questioned whether Jesus was the carpenter's son when he taught in his hometown?",
    "option_a": "Disciples",
    "option_b": "People of Nazareth",
    "option_c": "Pharisees",
    "option_d": "Sadducees",
    "correct_answer": "People of Nazareth",
    "difficulty": "hard",
    "tags": ["matthew", "people_of_nazareth", "hometown", "speaker_recognition"],
    "source_key": "matthew-016-nazareth-carpenters-son"
  },
  {
    "type": "who_said_it",
    "book": "Matthew",
    "book_order": 40,
    "testament": "new_testament",
    "category": "gospels",
    "speaker": "Jesus",
    "speaker_type": "person",
    "reference": "Matthew 14:27",
    "quote_text": "Take heart, it is I; do not be afraid.",
    "prompt_context": "While walking on the sea toward the boat, the speaker calmed the frightened disciples.",
    "question": "Who told the terrified disciples on the water, \"Take heart, it is I; do not be afraid\"?",
    "option_a": "Peter",
    "option_b": "John",
    "option_c": "Jesus",
    "option_d": "Angel of the Lord",
    "correct_answer": "Jesus",
    "difficulty": "easy",
    "tags": ["matthew", "jesus", "walking_on_water", "speaker_recognition"],
    "source_key": "matthew-017-jesus-it-is-i"
  },
  {
    "type": "who_said_it",
    "book": "Matthew",
    "book_order": 40,
    "testament": "new_testament",
    "category": "gospels",
    "speaker": "Canaanite Woman",
    "speaker_type": "person",
    "reference": "Matthew 15:27",
    "quote_text": "Even the dogs eat the crumbs that fall from their masters' table.",
    "prompt_context": "A Gentile woman responded humbly and boldly when Jesus tested her persistence.",
    "question": "Who answered Jesus by saying that even dogs eat the crumbs from their masters' table?",
    "option_a": "Mary Magdalene",
    "option_b": "Canaanite Woman",
    "option_c": "Martha",
    "option_d": "Mother of James and John",
    "correct_answer": "Canaanite Woman",
    "difficulty": "medium",
    "tags": ["matthew", "canaanite_woman", "faith", "speaker_recognition"],
    "source_key": "matthew-018-canaanite-woman-crumbs"
  },
  {
    "type": "who_said_it",
    "book": "Matthew",
    "book_order": 40,
    "testament": "new_testament",
    "category": "gospels",
    "speaker": "Jesus",
    "speaker_type": "person",
    "reference": "Matthew 16:15",
    "quote_text": "Who do you say that I am?",
    "prompt_context": "At Caesarea Philippi, after asking what others were saying about him, the teacher turned the question on his disciples.",
    "question": "Who asked the disciples at Caesarea Philippi who they said he was?",
    "option_a": "Peter",
    "option_b": "Jesus",
    "option_c": "John the Baptist",
    "option_d": "Andrew",
    "correct_answer": "Jesus",
    "difficulty": "medium",
    "tags": ["matthew", "jesus", "caesarea_philippi", "speaker_recognition"],
    "source_key": "matthew-019-jesus-who-do-you-say"
  },
  {
    "type": "who_said_it",
    "book": "Matthew",
    "book_order": 40,
    "testament": "new_testament",
    "category": "gospels",
    "speaker": "Peter",
    "speaker_type": "person",
    "reference": "Matthew 16:22",
    "quote_text": "God forbid it, Lord! This must never happen to you.",
    "prompt_context": "After Jesus predicted his suffering and death, one disciple rebuked him.",
    "question": "Who tried to stop Jesus after he spoke about his coming suffering and death?",
    "option_a": "James",
    "option_b": "John",
    "option_c": "Peter",
    "option_d": "Thomas",
    "correct_answer": "Peter",
    "difficulty": "medium",
    "tags": ["matthew", "peter", "passion_prediction", "speaker_recognition"],
    "source_key": "matthew-020-peter-this-must-never-happen"
  },
  {
    "type": "who_said_it",
    "book": "Matthew",
    "book_order": 40,
    "testament": "new_testament",
    "category": "gospels",
    "speaker": "Voice from the Cloud",
    "speaker_type": "divine",
    "reference": "Matthew 17:5",
    "quote_text": "This is my Son, the Beloved; with him I am well pleased; listen to him!",
    "prompt_context": "On the mountain, while Peter was still speaking, a heavenly voice interrupted the moment.",
    "question": "Who spoke from the bright cloud at the transfiguration, telling the disciples to listen to Jesus?",
    "option_a": "Moses",
    "option_b": "Elijah",
    "option_c": "Angel of the Lord",
    "option_d": "Voice from the Cloud",
    "correct_answer": "Voice from the Cloud",
    "difficulty": "hard",
    "tags": ["matthew", "voice_from_the_cloud", "transfiguration", "speaker_recognition"],
    "source_key": "matthew-021-voice-cloud-listen-to-him"
  },
  {
    "type": "who_said_it",
    "book": "Matthew",
    "book_order": 40,
    "testament": "new_testament",
    "category": "gospels",
    "speaker": "Disciples",
    "speaker_type": "group",
    "reference": "Matthew 17:19",
    "quote_text": "Why could we not cast it out?",
    "prompt_context": "After Jesus healed a boy whom they had failed to help, the disciples asked privately about their failure.",
    "question": "Who asked Jesus privately why they had been unable to cast out the demon?",
    "option_a": "Scribes",
    "option_b": "Disciples",
    "option_c": "Crowd",
    "option_d": "Pharisees",
    "correct_answer": "Disciples",
    "difficulty": "hard",
    "tags": ["matthew", "disciples", "private_question", "speaker_recognition"],
    "source_key": "matthew-022-disciples-why-could-we-not"
  },
  {
    "type": "who_said_it",
    "book": "Matthew",
    "book_order": 40,
    "testament": "new_testament",
    "category": "gospels",
    "speaker": "Jesus",
    "speaker_type": "person",
    "reference": "Matthew 18:3",
    "quote_text": "Unless you change and become like children, you will never enter the kingdom of heaven.",
    "prompt_context": "When the disciples asked about greatness, the teacher answered by setting a child before them.",
    "question": "Who told the disciples they must become like children to enter the kingdom of heaven?",
    "option_a": "Peter",
    "option_b": "Jesus",
    "option_c": "John the Baptist",
    "option_d": "Moses",
    "correct_answer": "Jesus",
    "difficulty": "medium",
    "tags": ["matthew", "jesus", "greatness", "speaker_recognition"],
    "source_key": "matthew-023-jesus-become-like-children"
  },
  {
    "type": "who_said_it",
    "book": "Matthew",
    "book_order": 40,
    "testament": "new_testament",
    "category": "gospels",
    "speaker": "Peter",
    "speaker_type": "person",
    "reference": "Matthew 18:21",
    "quote_text": "How often should I forgive?",
    "prompt_context": "After Jesus taught about dealing with sin, one disciple asked about the limits of forgiveness.",
    "question": "Who asked Jesus how many times he should forgive a brother or sister who sins against him?",
    "option_a": "John",
    "option_b": "Peter",
    "option_c": "James",
    "option_d": "Matthew",
    "correct_answer": "Peter",
    "difficulty": "medium",
    "tags": ["matthew", "peter", "forgiveness", "speaker_recognition"],
    "source_key": "matthew-024-peter-how-often-forgive"
  },
  {
    "type": "who_said_it",
    "book": "Matthew",
    "book_order": 40,
    "testament": "new_testament",
    "category": "gospels",
    "speaker": "Rich Young Man",
    "speaker_type": "person",
    "reference": "Matthew 19:16",
    "quote_text": "What good deed must I do to have eternal life?",
    "prompt_context": "A wealthy young man approached Jesus with a question about inheriting life.",
    "question": "Who asked Jesus what good deed he must do to have eternal life?",
    "option_a": "Nicodemus",
    "option_b": "Rich Young Man",
    "option_c": "Centurion",
    "option_d": "Tax Collector",
    "correct_answer": "Rich Young Man",
    "difficulty": "easy",
    "tags": ["matthew", "rich_young_man", "eternal_life", "speaker_recognition"],
    "source_key": "matthew-025-rich-young-man-eternal-life"
  },
  {
    "type": "who_said_it",
    "book": "Matthew",
    "book_order": 40,
    "testament": "new_testament",
    "category": "gospels",
    "speaker": "Mother of James and John",
    "speaker_type": "person",
    "reference": "Matthew 20:21",
    "quote_text": "Declare that these two sons of mine will sit, one at your right hand and one at your left.",
    "prompt_context": "A mother approached Jesus asking for places of honor for her sons in his kingdom.",
    "question": "Who asked Jesus for her two sons to sit at his right and left in his kingdom?",
    "option_a": "Mary Magdalene",
    "option_b": "Mother of James and John",
    "option_c": "Martha",
    "option_d": "Herodias",
    "correct_answer": "Mother of James and John",
    "difficulty": "hard",
    "tags": ["matthew", "mother_of_james_and_john", "kingdom", "speaker_recognition"],
    "source_key": "matthew-026-mother-right-and-left"
  },
  {
    "type": "who_said_it",
    "book": "Matthew",
    "book_order": 40,
    "testament": "new_testament",
    "category": "gospels",
    "speaker": "Crowds",
    "speaker_type": "group",
    "reference": "Matthew 21:9",
    "quote_text": "Hosanna to the Son of David!",
    "prompt_context": "As Jesus entered Jerusalem, the people around him shouted messianic praise.",
    "question": "Who shouted \"Hosanna to the Son of David\" as Jesus entered Jerusalem?",
    "option_a": "Chief Priests",
    "option_b": "Disciples",
    "option_c": "Crowds",
    "option_d": "Soldiers",
    "correct_answer": "Crowds",
    "difficulty": "easy",
    "tags": ["matthew", "crowds", "triumphal_entry", "speaker_recognition"],
    "source_key": "matthew-027-crowds-hosanna-son-of-david"
  },
  {
    "type": "who_said_it",
    "book": "Matthew",
    "book_order": 40,
    "testament": "new_testament",
    "category": "gospels",
    "speaker": "Chief Priests and Elders",
    "speaker_type": "group",
    "reference": "Matthew 21:23",
    "quote_text": "By what authority are you doing these things?",
    "prompt_context": "In the temple courts, religious leaders confronted Jesus after his public actions and teaching.",
    "question": "Who challenged Jesus in the temple by asking by what authority he acted?",
    "option_a": "Sadducees",
    "option_b": "Chief Priests and Elders",
    "option_c": "Crowds",
    "option_d": "Herodians",
    "correct_answer": "Chief Priests and Elders",
    "difficulty": "medium",
    "tags": ["matthew", "chief_priests_and_elders", "temple", "speaker_recognition"],
    "source_key": "matthew-028-chief-priests-authority-question"
  },
  {
    "type": "who_said_it",
    "book": "Matthew",
    "book_order": 40,
    "testament": "new_testament",
    "category": "gospels",
    "speaker": "Jesus",
    "speaker_type": "person",
    "reference": "Matthew 22:21",
    "quote_text": "Give therefore to the emperor the things that are the emperor's.",
    "prompt_context": "After being asked about paying taxes to Caesar, the teacher answered with a famous distinction.",
    "question": "Who said to give to the emperor what belongs to the emperor and to God what belongs to God?",
    "option_a": "Paul",
    "option_b": "Peter",
    "option_c": "Jesus",
    "option_d": "John the Baptist",
    "correct_answer": "Jesus",
    "difficulty": "medium",
    "tags": ["matthew", "jesus", "taxes", "speaker_recognition"],
    "source_key": "matthew-029-jesus-give-to-caesar"
  },
  {
    "type": "who_said_it",
    "book": "Matthew",
    "book_order": 40,
    "testament": "new_testament",
    "category": "gospels",
    "speaker": "Sadducees",
    "speaker_type": "group",
    "reference": "Matthew 22:28",
    "quote_text": "In the resurrection, then, whose wife of the seven will she be?",
    "prompt_context": "A group that denied the resurrection tried to trap Jesus with a case about levirate marriage.",
    "question": "Who asked Jesus whose wife a woman would be in the resurrection after being married to seven brothers?",
    "option_a": "Pharisees",
    "option_b": "Scribes",
    "option_c": "Chief Priests",
    "option_d": "Sadducees",
    "correct_answer": "Sadducees",
    "difficulty": "hard",
    "tags": ["matthew", "sadducees", "resurrection", "speaker_recognition"],
    "source_key": "matthew-030-sadducees-whose-wife"
  },
  {
    "type": "who_said_it",
    "book": "Matthew",
    "book_order": 40,
    "testament": "new_testament",
    "category": "gospels",
    "speaker": "Lawyer",
    "speaker_type": "person",
    "reference": "Matthew 22:36",
    "quote_text": "Which commandment in the law is the greatest?",
    "prompt_context": "During a test question, a Pharisaic legal expert asked Jesus to identify the greatest commandment.",
    "question": "Who asked Jesus which commandment in the law was the greatest?",
    "option_a": "Lawyer",
    "option_b": "Young Ruler",
    "option_c": "Centurion",
    "option_d": "Scribe from Nazareth",
    "correct_answer": "Lawyer",
    "difficulty": "hard",
    "tags": ["matthew", "lawyer", "greatest_commandment", "speaker_recognition"],
    "source_key": "matthew-031-lawyer-greatest-commandment"
  },
  {
    "type": "who_said_it",
    "book": "Matthew",
    "book_order": 40,
    "testament": "new_testament",
    "category": "gospels",
    "speaker": "Jesus",
    "speaker_type": "person",
    "reference": "Matthew 23:27",
    "quote_text": "You are like whitewashed tombs.",
    "prompt_context": "In a public denunciation, the speaker condemned religious hypocrisy with striking imagery.",
    "question": "Who compared the scribes and Pharisees to whitewashed tombs?",
    "option_a": "John the Baptist",
    "option_b": "Peter",
    "option_c": "Jesus",
    "option_d": "Stephen",
    "correct_answer": "Jesus",
    "difficulty": "hard",
    "tags": ["matthew", "jesus", "scribes_and_pharisees", "speaker_recognition"],
    "source_key": "matthew-032-jesus-whitewashed-tombs"
  },
  {
    "type": "who_said_it",
    "book": "Matthew",
    "book_order": 40,
    "testament": "new_testament",
    "category": "gospels",
    "speaker": "Disciples",
    "speaker_type": "group",
    "reference": "Matthew 24:3",
    "quote_text": "What will be the sign of your coming and of the end of the age?",
    "prompt_context": "On the Mount of Olives, a private question followed Jesus' prediction about the temple.",
    "question": "Who privately asked Jesus about the sign of his coming and the end of the age?",
    "option_a": "Crowds",
    "option_b": "Chief Priests",
    "option_c": "Disciples",
    "option_d": "Roman Soldiers",
    "correct_answer": "Disciples",
    "difficulty": "hard",
    "tags": ["matthew", "disciples", "mount_of_olives", "speaker_recognition"],
    "source_key": "matthew-033-disciples-sign-of-coming"
  },
  {
    "type": "who_said_it",
    "book": "Matthew",
    "book_order": 40,
    "testament": "new_testament",
    "category": "gospels",
    "speaker": "Bridegroom",
    "speaker_type": "person",
    "reference": "Matthew 25:12",
    "quote_text": "Truly I tell you, I do not know you.",
    "prompt_context": "In the parable of the ten bridesmaids, a late group arrived after the door had been shut.",
    "question": "In the parable of the ten bridesmaids, who said, \"I do not know you\"?",
    "option_a": "Servant",
    "option_b": "Bridegroom",
    "option_c": "Master",
    "option_d": "Watchman",
    "correct_answer": "Bridegroom",
    "difficulty": "hard",
    "tags": ["matthew", "bridegroom", "parable", "speaker_recognition"],
    "source_key": "matthew-034-bridegroom-i-do-not-know-you"
  },
  {
    "type": "who_said_it",
    "book": "Matthew",
    "book_order": 40,
    "testament": "new_testament",
    "category": "gospels",
    "speaker": "Chief Priests",
    "speaker_type": "group",
    "reference": "Matthew 26:4",
    "quote_text": "They conspired to arrest Jesus by stealth and kill him.",
    "prompt_context": "Before Passover, the leaders plotted secretly against Jesus, though they wanted to avoid a public uproar.",
    "question": "Who plotted to arrest Jesus secretly and kill him before the feast?",
    "option_a": "Disciples",
    "option_b": "Herodians",
    "option_c": "Chief Priests",
    "option_d": "Crowds",
    "correct_answer": "Chief Priests",
    "difficulty": "hard",
    "tags": ["matthew", "chief_priests", "plot", "speaker_recognition"],
    "source_key": "matthew-035-chief-priests-plot-secretly"
  },
  {
    "type": "who_said_it",
    "book": "Matthew",
    "book_order": 40,
    "testament": "new_testament",
    "category": "gospels",
    "speaker": "Disciples",
    "speaker_type": "group",
    "reference": "Matthew 26:22",
    "quote_text": "Surely not I, Lord?",
    "prompt_context": "At the supper, after Jesus announced that one of them would betray him, the table reacted one by one.",
    "question": "Who repeatedly asked Jesus, \"Surely not I, Lord?\" after he said one of them would betray him?",
    "option_a": "Pharisees",
    "option_b": "Women who followed him",
    "option_c": "Disciples",
    "option_d": "Servants",
    "correct_answer": "Disciples",
    "difficulty": "hard",
    "tags": ["matthew", "disciples", "last_supper", "speaker_recognition"],
    "source_key": "matthew-036-disciples-surely-not-i"
  },
  {
    "type": "who_said_it",
    "book": "Matthew",
    "book_order": 40,
    "testament": "new_testament",
    "category": "gospels",
    "speaker": "Judas",
    "speaker_type": "person",
    "reference": "Matthew 26:25",
    "quote_text": "Surely not I, Rabbi?",
    "prompt_context": "At the same meal, one disciple addressed Jesus differently while asking if he was the betrayer.",
    "question": "Who said to Jesus, \"Surely not I, Rabbi?\" at the supper?",
    "option_a": "Peter",
    "option_b": "John",
    "option_c": "Judas",
    "option_d": "Thomas",
    "correct_answer": "Judas",
    "difficulty": "hard",
    "tags": ["matthew", "judas", "last_supper", "speaker_recognition"],
    "source_key": "matthew-037-judas-surely-not-i-rabbi"
  },
  {
    "type": "who_said_it",
    "book": "Matthew",
    "book_order": 40,
    "testament": "new_testament",
    "category": "gospels",
    "speaker": "Jesus",
    "speaker_type": "person",
    "reference": "Matthew 26:31",
    "quote_text": "You will all become deserters because of me this night.",
    "prompt_context": "On the way to the Mount of Olives, the teacher warned his followers that they would scatter.",
    "question": "Who told the disciples that they would all fall away that night?",
    "option_a": "Peter",
    "option_b": "Jesus",
    "option_c": "John the Baptist",
    "option_d": "High Priest",
    "correct_answer": "Jesus",
    "difficulty": "medium",
    "tags": ["matthew", "jesus", "mount_of_olives", "speaker_recognition"],
    "source_key": "matthew-038-jesus-you-will-all-fall-away"
  },
  {
    "type": "who_said_it",
    "book": "Matthew",
    "book_order": 40,
    "testament": "new_testament",
    "category": "gospels",
    "speaker": "Peter",
    "speaker_type": "person",
    "reference": "Matthew 26:35",
    "quote_text": "Even though I must die with you, I will not deny you.",
    "prompt_context": "After Jesus predicted denial, one disciple insisted on his loyalty more strongly than the rest.",
    "question": "Who vowed to Jesus that he would not deny him even if he had to die with him?",
    "option_a": "Thomas",
    "option_b": "James",
    "option_c": "Peter",
    "option_d": "Andrew",
    "correct_answer": "Peter",
    "difficulty": "medium",
    "tags": ["matthew", "peter", "denial", "speaker_recognition"],
    "source_key": "matthew-039-peter-i-will-not-deny"
  },
  {
    "type": "who_said_it",
    "book": "Matthew",
    "book_order": 40,
    "testament": "new_testament",
    "category": "gospels",
    "speaker": "Jesus",
    "speaker_type": "person",
    "reference": "Matthew 26:39",
    "quote_text": "My Father, if it is possible, let this cup pass from me.",
    "prompt_context": "In Gethsemane, the speaker prayed in deep anguish while submitting to the Father's will.",
    "question": "Who prayed in Gethsemane that the cup might pass, yet asked for the Father's will to be done?",
    "option_a": "Peter",
    "option_b": "Judas",
    "option_c": "Jesus",
    "option_d": "John",
    "correct_answer": "Jesus",
    "difficulty": "medium",
    "tags": ["matthew", "jesus", "gethsemane", "speaker_recognition"],
    "source_key": "matthew-040-jesus-let-this-cup-pass"
  },
  {
    "type": "who_said_it",
    "book": "Matthew",
    "book_order": 40,
    "testament": "new_testament",
    "category": "gospels",
    "speaker": "Jesus",
    "speaker_type": "person",
    "reference": "Matthew 26:50",
    "quote_text": "Friend, do what you are here to do.",
    "prompt_context": "At the moment of betrayal in the garden, Jesus addressed the one who approached him with a kiss.",
    "question": "Who said, \"Friend, do what you are here to do\" when Judas arrived in Gethsemane?",
    "option_a": "Peter",
    "option_b": "Jesus",
    "option_c": "High Priest",
    "option_d": "Angel of the Lord",
    "correct_answer": "Jesus",
    "difficulty": "hard",
    "tags": ["matthew", "jesus", "judas", "speaker_recognition"],
    "source_key": "matthew-041-jesus-friend-do-what-you-came"
  },
  {
    "type": "who_said_it",
    "book": "Matthew",
    "book_order": 40,
    "testament": "new_testament",
    "category": "gospels",
    "speaker": "High Priest",
    "speaker_type": "person",
    "reference": "Matthew 26:63",
    "quote_text": "Tell us if you are the Messiah, the Son of God.",
    "prompt_context": "During the hearing before the council, the presiding religious leader directly questioned Jesus under oath.",
    "question": "Who directly asked Jesus whether he was the Messiah, the Son of God, at the hearing?",
    "option_a": "Pilate",
    "option_b": "Chief Priest's Servant",
    "option_c": "High Priest",
    "option_d": "Judas",
    "correct_answer": "High Priest",
    "difficulty": "hard",
    "tags": ["matthew", "high_priest", "trial", "speaker_recognition"],
    "source_key": "matthew-042-high-priest-are-you-messiah"
  },
  {
    "type": "who_said_it",
    "book": "Matthew",
    "book_order": 40,
    "testament": "new_testament",
    "category": "gospels",
    "speaker": "Servant Girl",
    "speaker_type": "person",
    "reference": "Matthew 26:69",
    "quote_text": "You also were with Jesus the Galilean.",
    "prompt_context": "While Peter sat outside in the courtyard, a young female accuser spoke first.",
    "question": "Who first told Peter in the courtyard that he had been with Jesus the Galilean?",
    "option_a": "Servant Girl",
    "option_b": "Roman Soldier",
    "option_c": "Chief Priest",
    "option_d": "John",
    "correct_answer": "Servant Girl",
    "difficulty": "hard",
    "tags": ["matthew", "servant_girl", "peter", "speaker_recognition"],
    "source_key": "matthew-043-servant-girl-you-were-with-jesus"
  },
  {
    "type": "who_said_it",
    "book": "Matthew",
    "book_order": 40,
    "testament": "new_testament",
    "category": "gospels",
    "speaker": "Judas",
    "speaker_type": "person",
    "reference": "Matthew 27:4",
    "quote_text": "I have sinned by betraying innocent blood.",
    "prompt_context": "After seeing that Jesus was condemned, the betrayer returned the silver and confessed his guilt.",
    "question": "Who confessed, \"I have sinned by betraying innocent blood\"?",
    "option_a": "Peter",
    "option_b": "Pilate",
    "option_c": "Judas",
    "option_d": "Centurion",
    "correct_answer": "Judas",
    "difficulty": "medium",
    "tags": ["matthew", "judas", "silver", "speaker_recognition"],
    "source_key": "matthew-044-judas-betraying-innocent-blood"
  },
  {
    "type": "who_said_it",
    "book": "Matthew",
    "book_order": 40,
    "testament": "new_testament",
    "category": "gospels",
    "speaker": "Chief Priests",
    "speaker_type": "group",
    "reference": "Matthew 27:6",
    "quote_text": "It is not lawful to put them into the treasury.",
    "prompt_context": "After Judas threw down the silver, the temple authorities debated what to do with the money.",
    "question": "Who said it was not lawful to put the returned silver into the treasury?",
    "option_a": "Pharisees",
    "option_b": "Scribes",
    "option_c": "Chief Priests",
    "option_d": "Elders of the People",
    "correct_answer": "Chief Priests",
    "difficulty": "hard",
    "tags": ["matthew", "chief_priests", "silver", "speaker_recognition"],
    "source_key": "matthew-045-chief-priests-not-lawful-treasury"
  },
  {
    "type": "who_said_it",
    "book": "Matthew",
    "book_order": 40,
    "testament": "new_testament",
    "category": "gospels",
    "speaker": "Pilate's Wife",
    "speaker_type": "person",
    "reference": "Matthew 27:19",
    "quote_text": "Have nothing to do with that innocent man.",
    "prompt_context": "While Pilate was seated on the judgment bench, a warning came to him because of a troubling dream.",
    "question": "Who sent Pilate a warning to have nothing to do with Jesus?",
    "option_a": "Mary",
    "option_b": "Pilate's Wife",
    "option_c": "Claudia the Servant",
    "option_d": "Herodias",
    "correct_answer": "Pilate's Wife",
    "difficulty": "hard",
    "tags": ["matthew", "pilates_wife", "dream", "speaker_recognition"],
    "source_key": "matthew-046-pilates-wife-innocent-man"
  },
  {
    "type": "who_said_it",
    "book": "Matthew",
    "book_order": 40,
    "testament": "new_testament",
    "category": "gospels",
    "speaker": "Crowd",
    "speaker_type": "group",
    "reference": "Matthew 27:25",
    "quote_text": "His blood be on us and on our children!",
    "prompt_context": "During the trial before Pilate, the assembled people answered in a dark and memorable way.",
    "question": "Who cried out, \"His blood be on us and on our children\"?",
    "option_a": "Chief Priests",
    "option_b": "Soldiers",
    "option_c": "Crowd",
    "option_d": "Disciples",
    "correct_answer": "Crowd",
    "difficulty": "hard",
    "tags": ["matthew", "crowd", "pilate", "speaker_recognition"],
    "source_key": "matthew-047-crowd-his-blood-on-us"
  },
  {
    "type": "who_said_it",
    "book": "Matthew",
    "book_order": 40,
    "testament": "new_testament",
    "category": "gospels",
    "speaker": "Soldiers",
    "speaker_type": "group",
    "reference": "Matthew 27:29",
    "quote_text": "Hail, King of the Jews!",
    "prompt_context": "After dressing Jesus in a robe and crown of thorns, the governor's soldiers mocked him.",
    "question": "Who mockingly hailed Jesus as King of the Jews after putting a crown of thorns on him?",
    "option_a": "Crowd",
    "option_b": "Chief Priests",
    "option_c": "Soldiers",
    "option_d": "Disciples",
    "correct_answer": "Soldiers",
    "difficulty": "medium",
    "tags": ["matthew", "soldiers", "mocking", "speaker_recognition"],
    "source_key": "matthew-048-soldiers-hail-king-of-jews"
  },
  {
    "type": "who_said_it",
    "book": "Matthew",
    "book_order": 40,
    "testament": "new_testament",
    "category": "gospels",
    "speaker": "Bystanders",
    "speaker_type": "group",
    "reference": "Matthew 27:47",
    "quote_text": "This man is calling for Elijah.",
    "prompt_context": "As Jesus cried out on the cross, some people nearby misunderstood what they heard.",
    "question": "Who said that Jesus was calling for Elijah while he was on the cross?",
    "option_a": "Disciples",
    "option_b": "Bystanders",
    "option_c": "Chief Priests",
    "option_d": "Women at the Cross",
    "correct_answer": "Bystanders",
    "difficulty": "hard",
    "tags": ["matthew", "bystanders", "crucifixion", "speaker_recognition"],
    "source_key": "matthew-049-bystanders-calling-for-elijah"
  },
  {
    "type": "who_said_it",
    "book": "Matthew",
    "book_order": 40,
    "testament": "new_testament",
    "category": "gospels",
    "speaker": "Angel of the Lord",
    "speaker_type": "angel",
    "reference": "Matthew 28:5",
    "quote_text": "Do not be afraid.",
    "prompt_context": "At the empty tomb, a heavenly messenger spoke to the women and explained that Jesus had been raised.",
    "question": "Who told the women at the tomb not to be afraid and announced that Jesus had been raised?",
    "option_a": "Jesus",
    "option_b": "Mary Magdalene",
    "option_c": "Angel of the Lord",
    "option_d": "Peter",
    "correct_answer": "Angel of the Lord",
    "difficulty": "easy",
    "tags": ["matthew", "angel_of_the_lord", "empty_tomb", "speaker_recognition"],
    "source_key": "matthew-050-angel-tomb-do-not-be-afraid"
  }
]